{
  "components": [
   {
     "id": "aIMnm2re1exM1M7pEEur9",
    "type": "collapsiblePanel",
    "propertyName": "pnlDisplay",
    "label": "Display",
    "labelAlign": "right",
    "parentId": "root",
    "hidden": false,

    "isDynamic": false,
    "version": 2,
    "expandIconPosition": "left",
    "collapsible": "header",
    "ghost": true,
    "hideWhenEmpty": true,
    "settingsValidationErrors": [],
    "header": {
      "id": "FizvoIoyeq1cZMqAgbDLL",
      "components": []
    },
    "content": {
      "id": "y9SNudmMM0Wd1Sc_YI1ng",
      "components": [
    {
      "id": "5c813b1a-04c5-4658-ac0f-cbcbae6b3bd4",
      "type": "contextPropertyAutocomplete",
      "propertyName": "propertyName",
      "parentId": "root",
      "label": "Property name",
      "validate": {
        "required": true
      }
    },
    {
      "id": "46d07439-4c18-468c-89e1-60c002ce96c5",
      "type": "textField",
      "propertyName": "label",
      "parentId": "root",
      "label": "Label"
    },
    {
      "id": "cfd7d45e-c7e3-4a27-987b-dc525c412448",
      "type": "checkbox",
      "propertyName": "hidden",
      "parentId": "root",
      "label": "Hidden"
    },
    {
      "id": "c6885251-96a6-40ce-99b2-4b5209a9e01c",
      "type": "checkbox",
      "propertyName": "hideLabel",
      "parentId": "root",
      "label": "Hide Label"
    },
    {
      "id": "24a8be15-98eb-40f7-99ea-ebb602693e9c",
      "type": "editModeSelector",
      "propertyName": "editMode",
      "parentId": "root",
      "label": "Edit mode"
    }
      ]
    }
},
{
  "id": "kp3afwRnhZk2958QCUvFTFeGWOokZY",
  "type": "propertyRouter",
  "propertyName": "propertyRouter1",
  "componentName": "propertyRouter1",
  "label": "Property router1",
  "labelAlign": "right",
  "parentId": "root",
  "hidden": false,
  "isDynamic": false,
  "propertyRouteName": {
    "_mode": "code",
    "_code": "    return contexts.canvasContext?.designerDevice || 'desktop';",
    "_value": ""
  },
  "components": [
{
  "id": "aIMnm2re2exM1M7pEEur9",
 "type": "collapsiblePanel",
 "propertyName": "pnlStyle",
 "label": "Style",
 "labelAlign": "right",
 "parentId": "root",
 "hidden": false,

 "isDynamic": false,
 "version": 2,
 "expandIconPosition": "left",
 "collapsible": "header",
 "ghost": true,
 "hideWhenEmpty": true,
 "settingsValidationErrors": [],
 "header": {
   "id": "FhzvoIoyeq1cZMqAgbDLL",
   "components": []
 },
 "content": {
   "id": "y9SMudmMM0Wd1Sc_YI1ng",
   "components": [
    {
      "id": "06ab0599-914d-4d2d-875c-765a495472f8",
      "type": "codeEditor",
      "propertyName": "style",
      "label": "Style",
      "parentId": "root",
      "validate": {},
      "settingsValidationErrors": [],
      "description": "A script that returns the style of the element as an object. This should conform to CSSProperties",
      "exposedVariables": [{ "name": "data", "description": "Form values", "type": "object" }]
    },
    {
      "id": "8615d12f-6ea0-4b11-a1a1-6088c7160fd9",
      "type": "dropdown",
      "propertyName": "size",
      "parentId": "root",
      "label": "Size",
      "allowClear": true,
      "values": [
        {
          "label": "Small",
          "value": "small",
          "id": "4f11403c-95fd-4e49-bb60-cb8c25f0f3c3"
        },
        {
          "label": "Default",
          "value": "default",
          "id": "8f85c476-e632-4fa7-89ad-2be6cfb7f1f1"
        }
      ],
      "dataSourceType": "values"
    }
  ]
}
}
]
},
{
  "id": "6Vw9iiDw9d0MD_Rh5cbIn",
  "type": "collapsiblePanel",
  "propertyName": "pnlSecurity",
  "label": "Security",
  "labelAlign": "right",
  "parentId": "root",
  "isDynamic": false,
  "version": 4,
  "expandIconPosition": "start",
  "header": {
    "id": "mbzE03mJnv_89oUvkmjPs",
    "components": []
  },
  "content": {
    "id": "SsWPpiJfTbgl4iHlFA_or",
    "components": [
      {
        "id": "1adea529-1f0c-4def-bd41-ee166a5dfcd7",
        "type": "permissionAutocomplete",
        "propertyName": "permissions",
        "parentId": "SsWPpiJfTbgl4iHlFA_or",
        "label": "Permissions",
        "validate": {},
        "version": 1
      }
    ]
  },
  "collapsible": "header",
  "ghost": true,
  "hideWhenEmpty": true,
  "settingsValidationErrors": []
}
  ],
  
  "formSettings": {
    "layout": "horizontal",
    "colon": true,
    "labelCol": {
      "span": 8
    },
    "wrapperCol": {
      "span": 16
    },
    "displayName": "DEFAULT_FORM_SETTINGS",
    "__docgenInfo": {
      "description": "Default form settings",
      "displayName": "DEFAULT_FORM_SETTINGS",
      "props": {}
    }
  }
}
